SignalIntegrity/__about__.py
SignalIntegrity/__init__.py
SignalIntegrity/rebase.py
SignalIntegrity/App/About.py
SignalIntegrity/App/Archive.py
SignalIntegrity/App/BathtubCurveDialog.py
SignalIntegrity/App/BuildHelpSystem.py
SignalIntegrity/App/CalculationPropertiesDialog.py
SignalIntegrity/App/CalculationPropertiesProject.py
SignalIntegrity/App/Device.py
SignalIntegrity/App/DeviceExtendedConfiguration.py
SignalIntegrity/App/DeviceNetListLine.py
SignalIntegrity/App/DevicePicker.py
SignalIntegrity/App/DeviceProperties.py
SignalIntegrity/App/Drawing.py
SignalIntegrity/App/DrawingStateMachine.py
SignalIntegrity/App/EquationsDialog.py
SignalIntegrity/App/EyeDiagram.py
SignalIntegrity/App/EyeDiagramConfiguration.py
SignalIntegrity/App/EyeDiagramDialog.py
SignalIntegrity/App/EyeDiagramMeasurementsDialog.py
SignalIntegrity/App/EyeDiagramPropertiesDialog.py
SignalIntegrity/App/FilePicker.py
SignalIntegrity/App/Files.py
SignalIntegrity/App/HeaderDialog.py
SignalIntegrity/App/History.py
SignalIntegrity/App/InformationMessage.py
SignalIntegrity/App/MenuSystemHelpers.py
SignalIntegrity/App/NetList.py
SignalIntegrity/App/NetListDialog.py
SignalIntegrity/App/NetworkAnalyzer.py
SignalIntegrity/App/PartPicture.py
SignalIntegrity/App/PartPin.py
SignalIntegrity/App/PartProperty.py
SignalIntegrity/App/PlotWindow.py
SignalIntegrity/App/PostProcessingDialog.py
SignalIntegrity/App/Preferences.py
SignalIntegrity/App/PreferencesDialog.py
SignalIntegrity/App/PreferencesFile.py
SignalIntegrity/App/ProgressDialog.py
SignalIntegrity/App/Project.py
SignalIntegrity/App/ProjectFile.py
SignalIntegrity/App/ProjectFileBase.py
SignalIntegrity/App/Result.py
SignalIntegrity/App/SParameterProperties.py
SignalIntegrity/App/SParameterPropertiesDialog.py
SignalIntegrity/App/SParameterViewerPreferencesDialog.py
SignalIntegrity/App/SParameterViewerWindow.py
SignalIntegrity/App/Schematic.py
SignalIntegrity/App/SignalIntegrityApp.py
SignalIntegrity/App/SignalIntegrityAppHeadless.py
SignalIntegrity-1.5.0.dist-info/LICENSE.txt
SignalIntegrity-1.5.0.dist-info/METADATA
SignalIntegrity-1.5.0.dist-info/WHEEL
SignalIntegrity-1.5.0.dist-info/entry_points.txt
SignalIntegrity-1.5.0.dist-info/top_level.txt
SignalIntegrity-1.5.0.dist-info/RECORD
