Metadata-Version: 2.1
Name: SignalIntegrity
Version: 1.5.0
Summary: Signal and Power Integrity Tools
Home-page: https://github.com/Nubis-Communications/SignalIntegrity
Author: Peter J. Pupalaikis
Author-email: pete_pope@hotmail.com
License: License :: OSI Approved :: GNU General Public License v3 or later (GPLv3+)
Platform: UNKNOWN
Classifier: Development Status :: 5 - Production/Stable
Classifier: License :: OSI Approved :: GNU General Public License v3 or later (GPLv3+)
Classifier: Operating System :: OS Independent
Classifier: Programming Language :: Python
Classifier: Programming Language :: Python :: 3
Classifier: Programming Language :: Python :: 3.8
Classifier: Programming Language :: Python :: 3.9
Classifier: Programming Language :: Python :: 3.10
Classifier: Programming Language :: Python :: 3.11
Classifier: Topic :: Scientific/Engineering :: Electronic Design Automation (EDA)
Classifier: Topic :: Scientific/Engineering
Requires-Python: >=3.6
Requires-Dist: setuptools (>=58.2.0)
Requires-Dist: pip (>=20.2.4)
Requires-Dist: numpy (<=1.26.6,>=1.13.0)
Requires-Dist: matplotlib (>=2.2.3)
Requires-Dist: urllib3 (>=1.22.0)
Requires-Dist: Pillow (>=5.4.1)
Requires-Dist: scipy (>=1.2.1)
